pypozyx/__init__.py
pypozyx/core.py
pypozyx/lib.py
pypozyx/pozyx_i2c.py
pypozyx/pozyx_serial.py
pypozyx/definitions/__init__.py
pypozyx/definitions/bitmasks.py
pypozyx/definitions/constants.py
pypozyx/definitions/registers.py
pypozyx/structures/__init__.py
pypozyx/structures/byte_structure.py
pypozyx/structures/device.py
pypozyx/structures/device_information.py
pypozyx/structures/generic.py
pypozyx/structures/sensor_data.py
pypozyx/tools/__init__.py
pypozyx/tools/discover_all_devices.py
pypozyx/tools/version_check.py
pypozyx-1.2.5.dist-info/METADATA
pypozyx-1.2.5.dist-info/RECORD
pypozyx-1.2.5.dist-info/WHEEL
pypozyx-1.2.5.dist-info/top_level.txt
