Metadata-Version: 2.1
Name: pypozyx
Version: 1.2.5
Summary: Python library for Pozyx devices
Home-page: https://github.com/pozyxLabs/Pozyx-Python-library
Author: Laurent Van Acker
Author-email: laurent@pozyx.io
License: GPLv3
Download-URL: https://github.com/pozyxLabs/Pozyx-Python-library/archive/v1.2.5.tar.gz
Keywords: pozyx,serial,positioning,localisation
Platform: UNKNOWN
Classifier: Programming Language :: Python
Classifier: Development Status :: 5 - Production/Stable
Classifier: Intended Audience :: End Users/Desktop
Classifier: Operating System :: OS Independent
Classifier: License :: OSI Approved :: GNU General Public License v3 (GPLv3)
Classifier: Topic :: Software Development :: Libraries :: Python Modules
Classifier: Topic :: Scientific/Engineering
Requires-Dist: pyserial (>=3.0)
